Metadata-Version: 1.1
Name: pyramid-crud
Version: 0.1.3
Summary: CRUD interface for the Pyramid Framework
Home-page: https://github.com/Javex/pyramid_crud
Author: Florian Ruechel
Author-email: pyramid_crud@googlegroups.com
License: MIT
Keywords: web wsgi pylons pyramid crud admin
Platform: UNKNOWN
Classifier: Intended Audience :: Developers
Classifier: Programming Language :: Python
Classifier: Programming Language :: Python :: 2.6
Classifier: Programming Language :: Python :: 2.7
Classifier: Programming Language :: Python :: 3
Classifier: Programming Language :: Python :: 3.3
Classifier: Framework :: Pylons
Classifier: License :: OSI Approved :: MIT License
